htr/__init__.py
htr/__main__.py
htr/core.py
htr-0.0.0.1.dist-info/METADATA
htr-0.0.0.1.dist-info/WHEEL
htr-0.0.0.1.dist-info/entry_points.txt
htr-0.0.0.1.dist-info/top_level.txt
htr-0.0.0.1.dist-info/RECORD
