Metadata-Version: 2.1
Name: htr
Version: 0.0.0.1
Summary: HTR
Author-email: Grigori Fursin <gfursin@cknowledge.org>
License: Apache Software License (Apache 2.0)
Project-URL: Homepage, https://howtorun.io
Project-URL: Source, https://github.com/how-to-run/htr
Keywords: htr
Classifier: Development Status :: 3 - Alpha
Classifier: Intended Audience :: Developers
Classifier: Intended Audience :: End Users/Desktop
Classifier: Intended Audience :: Science/Research
Classifier: Intended Audience :: Information Technology
Classifier: Topic :: Software Development
Classifier: Topic :: System
Classifier: Topic :: Scientific/Engineering
Classifier: Operating System :: OS Independent
Classifier: Programming Language :: Python :: 3.8
Classifier: Programming Language :: Python :: 3.9
Classifier: Programming Language :: Python :: 3.10
Classifier: Programming Language :: Python :: 3.11
Classifier: Programming Language :: Python :: 3.12
Requires-Python: >=3.8
Requires-Dist: pyyaml
Requires-Dist: requests
Requires-Dist: setuptools
